Workbook

Sheet Helper Sheet
A1: COMPANIES | C1: TENDERS | E1: STATE | G1: MONTH & YEAR | I1: MONTHS | L1: TENDER ID | O1: MONTH START
A2: {=SORT(UNIQUE('Company Master Data'!B3:B1000),1,TRUE)} -> ABC Facility Solutions | C2: =IFERROR(__xludf.DUMMYFUNCTION("IFERROR(SORT(UNIQUE(FILTER('Tender Master Data'!D3:D1000, 'Tender Master Data'!C3:C1000 = DASHBOARD!A6))), """")"),"Campus Security") -> Campus Security | E2: {=SORT(UNIQUE('Company Master Data'!C3:C1000),1,TRUE)} -> Delhi | G2: {=UNIQUE('Tender Master Data'!H3:H1000)} -> Apr 2026 | I2: =IFERROR(__xludf.DUMMYFUNCTION("IFERROR(ARRAYFORMULA(TEXT(FILTER('Tender Master Data'!H3:H1000, 'Tender Master Data'!C3:C1000=DASHBOARD!A6, 'Tender Master Data'!D3:D1000=DASHBOARD!A8), ""mmm yyyy"")), """")"),"Jun 2026") -> Jun 2026 | K2: =ISTEXT(I2) -> TRUE | L2: =IFERROR(__xludf.DUMMYFUNCTION("IFERROR(FILTER('Tender Master Data'!A3:A1000, 'Tender Master Data'!C3:C1000=DASHBOARD!A6, 'Tender Master Data'!D3:D1000=DASHBOARD!A8), """")"),"T003") -> T003 | O2: =IFERROR(IF(ISNUMBER(DASHBOARD!A10), DATE(YEAR(DASHBOARD!A10), MONTH(DASHBOARD!A10), 1), DATEVALUE("1 "&DASHBOARD!A10)), "") -> 46174 | P2: =IFERROR(DATEVALUE("1 "&DASHBOARD!A10), "")
A3: Micky Services Pvt Ltd | C3: =IFERROR(__xludf.DUMMYFUNCTION("""COMPUTED_VALUE"""),"Office Cleaning") -> Office Cleaning | E3: Haryana | G3: May 2026
A4: XYZ Infra Services | E4: Maharashtra | G4: Jun 2026
G5: Jul 2026

Sheet DASHBOARD
A1: ="TENDER DASHBOARD| " & TEXT(TODAY(), "dd-mmmm-yyyy") -> TENDER DASHBOARD| 04-October-2026
A4: FILTERS
A5: COMPANY | E5: TOTAL RAR AMOUNT | H5: RECEIVED RAR | K5: PENDING RAR | N5: BALANCE IN BANK (ACCOUNT TO COMPANY )
A6: ABC Facility Solutions
A7: TENDER | E7: =SUMIFS('RA Bill Tracker'!G3:G999, 'RA Bill Tracker'!D3:D999, 'Helper Sheet'!L2) -> 600000 | H7: =SUMIFS('RA Bill Tracker'!H3:H999,'RA Bill Tracker'!D3:D999,'Helper Sheet'!L2) -> 200000 | K7: =SUMIFS('RA Bill Tracker'!I3:I999,'RA Bill Tracker'!D3:D999,'Helper Sheet'!L2) -> 400000 | N7: =SUMIFS('Bank Transactions'!H3:H999, 'Bank Transactions'!D3:D999, 'Helper Sheet'!L2, 'Bank Transactions'!G3:G999, "Opening Balance") + SUMIFS('Bank Transactions'!H3:H999, 'Bank Transactions'!D3:D999, 'Helper Sheet'!L2, 'Bank Transactions'!G3:G999, "Credit") - SUMIFS('Bank Transactions'!H3:H999, 'Bank Transactions'!D3:D999, 'Helper Sheet'!L2, 'Bank Transactions'!G3:G999, "Debit") -> 175000
A8: Campus Security
A9: MONTH
A10: 46174 | E10: SALARY ACCOUNT | H10: AMOUNT OF FDR OR BG | K10: SUPERVIOR ACCOUNT | N10: CONTRACT TIMELINE
A12: COMPANY DETAILS | E12: SALARY TRANSFER AMOUNT | F12: =SUMIFS('Salary Tracker'!H3:H999,'Salary Tracker'!D3:D999,'Helper Sheet'!$L$2) -> 24000 | H12: FDR AMOUNT | I12: =SUMIFS('FDR-BG Tracker'!G3:G999, 'FDR-BG Tracker'!C3:C999, 'Helper Sheet'!L2, 'FDR-BG Tracker'!F3:F999, "FDR")+SUMIFS('FDR-BG Tracker'!G3:G999, 'FDR-BG Tracker'!C3:C999, 'Helper Sheet'!L2, 'FDR-BG Tracker'!F3:F999, "BG") -> 150000 | K12: SUPERVISOR | L12: =IFERROR(__xludf.DUMMYFUNCTION("IFERROR(FILTER('Tender Master Data'!E3:E999, 'Tender Master Data'!C3:C999=DASHBOARD!A6, 'Tender Master Data'!D3:D999=DASHBOARD!A8), """")"),"Rohit") -> Rohit | N12: COMPLETED
A13: COMPANY & TENDER | E13: SALARY TRANSFER DATE | F13: =MAXIFS('Salary Tracker'!B3:B999, 'Salary Tracker'!D3:D999, 'Helper Sheet'!L2) -> 46174 | H13: FDR/BG | I13: =IFERROR(__xludf.DUMMYFUNCTION("IFERROR(TEXTJOIN("", "", TRUE, FILTER('FDR-BG Tracker'!F3:F999, 'FDR-BG Tracker'!C3:C999='Helper Sheet'!L2)), """")"),"BG") -> BG | K13: PAID TO SUPERVISOR | L13: =SUMIFS('Supervisor Tracker'!H3:H999, 'Supervisor Tracker'!D3:D999, 'Helper Sheet'!L2) -> 40000 | N13: =IF(OR(A22="", A24=""), "", MAX(0, MIN(1, (TODAY() - A22) / (IF(A26<>"", A26, A24) - A22)))) -> 0.58685446
A14: =$A$6&" | "&$A$8 -> ABC Facility Solutions | Campus Security | E14: ACTUAL AMOUNT | F14: =SUMIFS('Salary Tracker'!I3:I999,'Salary Tracker'!D3:D999,'Helper Sheet'!$L$2) -> 24000 | H14: FDR MADE BY | I14: =IFERROR(__xludf.DUMMYFUNCTION("IFERROR(TEXTJOIN("", "", TRUE, FILTER('FDR-BG Tracker'!H3:H999, 'FDR-BG Tracker'!C3:C999='Helper Sheet'!L2)), """")"),"HDFC") -> HDFC | N14: REMAINING
A15: COMPANY TENDER & MONTH | E15: BALANCE COLLECTION AMOUNT | F15: =SUMIFS('Salary Tracker'!J3:J999, 'Salary Tracker'!D3:D999, 'Helper Sheet'!L2) -> 0 | H15: FDR STATE | I15: =IFERROR(__xludf.DUMMYFUNCTION("IFERROR(TEXTJOIN("", "", TRUE, FILTER('FDR-BG Tracker'!K3:K999, 'FDR-BG Tracker'!C3:C999='Helper Sheet'!L2)), """")"),"Active") -> Active | K15: EXPENSE AND AMOUNT RETURNED | L15: =SUMIFS('Supervisor Tracker'!I3:I999, 'Supervisor Tracker'!D3:D999, 'Helper Sheet'!L2) + SUMIFS('Supervisor Tracker'!J3:J999, 'Supervisor Tracker'!D3:D999, 'Helper Sheet'!L2) -> 30000 | N15: =IF(N13="", "", 1 - N13) -> 0.41314554
A16: =A6&" | "&A8&" | "&IF(ISNUMBER(A10), TEXT(A10,"mmm yyyy"), A10) -> ABC Facility Solutions | Campus Security | Jun 2026 | E16: TOTAL EXPENSES | F16: =SUMIFS('Expense Tracker'!I3:I999, 'Expense Tracker'!D3:D999, 'Helper Sheet'!L2) -> 20200
A17: CA NUMBER | E17: EXPENSE ACCORDING TO MONTH | F17: =SUMIFS('Expense Tracker'!I3:I999, 'Expense Tracker'!D3:D999, 'Helper Sheet'!L2, 'Expense Tracker'!B3:B999, ">="&'Helper Sheet'!O2, 'Expense Tracker'!B3:B999, "<"&EDATE('Helper Sheet'!O2,1)) -> 18000 | H17: TOTAL SALARY TRANSFER AMOUNT | K17: BALANCE REMAINING AT SUPERVISOR | L17: =SUMIFS('Supervisor Tracker'!K3:K999, 'Supervisor Tracker'!D3:D999, 'Helper Sheet'!L2) -> 10000
E18: PER TENDER PROFIT | F18: =H7-F16-F14 -> 155800 | H18: =A6 -> ABC Facility Solutions
A19: CA AMOUNT | H19: =N7 -> 175000
A20: =IFERROR(__xludf.DUMMYFUNCTION("IFERROR(FILTER('Tender Master Data'!F3:F999, 'Tender Master Data'!C3:C999=A6, 'Tender Master Data'!D3:D999=A8), """")"),4000000.0) -> 4000000
A21: DATE OF COMMENCEMENT
A22: =IFERROR(__xludf.DUMMYFUNCTION("IFERROR(FILTER('Tender Master Data'!G3:G999, 'Tender Master Data'!C3:C999=A6, 'Tender Master Data'!D3:D999=A8), """")"),46174.0) -> 46174
A23: DATE OF COMPLETION
A24: =IFERROR(__xludf.DUMMYFUNCTION("IFERROR(FILTER('Tender Master Data'!I3:I999, 'Tender Master Data'!C3:C999=A6, 'Tender Master Data'!D3:D999=A8), """")"),46387.0) -> 46387
A25: EXTENDED DATE
A27: STATE
A28: =IFERROR(__xludf.DUMMYFUNCTION("IFERROR(FILTER('Company Master Data'!C3:C999, 'Company Master Data'!B3:B999=A6), """")"),"Delhi") -> Delhi

Sheet Company Master Data
A1: COMPANY MASTER
A2: Company ID | B2: Company Name | C2: State | D2: City | E2: Status
A3: C001 | B3: Micky Services Pvt Ltd | C3: Maharashtra | D3: Mumbai | E3: Active
A4: C002 | B4: ABC Facility Solutions | C4: Delhi | D4: New Delhi | E4: Active
A5: C003 | B5: XYZ Infra Services | C5: Haryana | D5: Gurugram | E5: Active

Sheet Tender Master Data
A1: TENDER MASTER
A2: Tender ID | B2: Company ID | C2: Company Name | D2: Tender Name | E2: Supervisor | F2: Contract Amount (₹) | G2: Start Date | H2: MONTH & YEAR | I2: End Date | J2: Status | K2: Location
A3: T001 | B3: C001 | C3: Micky Services Pvt Ltd | D3: Hospital Housekeeping | E3: Shivam | F3: 5000000 | G3: 46113 | H3: =TEXT(G3,"MMM YYY") -> Apr 2026 | I3: 46477 | J3: Active | K3: Mumbai
A4: T002 | B4: C001 | C4: Micky Services Pvt Ltd | D4: Office Manpower | E4: Rahul | F4: 3000000 | G4: 46143 | H4: =TEXT(G4,"MMM YYY") -> May 2026 | I4: 46507 | J4: Active | K4: Pune
A5: T003 | B5: C002 | C5: ABC Facility Solutions | D5: Campus Security | E5: Rohit | F5: 4000000 | G5: 46174 | H5: =TEXT(G5,"MMM YYY") -> Jun 2026 | I5: 46387 | J5: Active | K5: New Delhi
A6: T004 | B6: C002 | C6: ABC Facility Solutions | D6: Office Cleaning | E6: Amit | F6: 2500000 | G6: 46204 | H6: =TEXT(G6,"MMM YYY") -> Jul 2026 | I6: 46568 | J6: Active | K6: Noida
A7: T005 | B7: C003 | C7: XYZ Infra Services | D7: Road Maintenance | E7: Aman | F7: 3500000 | G7: 46127 | H7: =TEXT(G7,"MMM YYY") -> Apr 2026 | I7: 46491 | J7: Active | K7: Gurugram

Sheet RA Bill Tracker
A1: RA BILL TRACKER
A2: Bill No | B2: Bill Date | C2: Company ID | D2: Tender ID | E2: Company Name | F2: Tender Name | G2: Bill Amount (₹) | H2: Received (₹) | I2: Pending (₹) | J2: Last Received Date | K2: Status
A3: RA001 | B3: 46178 | C3: C001 | D3: T001 | E3: Micky Services Pvt Ltd | F3: =VLOOKUP(D3,TenderMaster[[Tender ID]:[Tender Name]],4,0) -> Hospital Housekeeping | G3: 500000 | H3: 300000 | I3: =G3-H3 -> 200000 | J3: 46193 | K3: Partially Received
A4: RA002 | B4: 46183 | C4: C001 | D4: T002 | E4: Micky Services Pvt Ltd | F4: =VLOOKUP(D4,TenderMaster[[Tender ID]:[Tender Name]],4,0) -> Office Manpower | G4: 400000 | H4: 400000 | I4: =G4-H4 -> 0 | J4: 46191 | K4: Received
A5: RA003 | B5: 46188 | C5: C002 | D5: T003 | E5: ABC Facility Solutions | F5: =VLOOKUP(D5,TenderMaster[[Tender ID]:[Tender Name]],4,0) -> Campus Security | G5: 600000 | H5: 200000 | I5: =G5-H5 -> 400000 | J5: 46198 | K5: Partially Received
A6: RA004 | B6: 46208 | C6: C002 | D6: T004 | E6: ABC Facility Solutions | F6: =VLOOKUP(D6,TenderMaster[[Tender ID]:[Tender Name]],4,0) -> Office Cleaning | G6: 350000 | H6: 0 | I6: =G6-H6 -> 350000 | K6: Pending
A7: RA005 | B7: 46215 | C7: C003 | D7: T005 | E7: XYZ Infra Services | F7: =VLOOKUP(D7,TenderMaster[[Tender ID]:[Tender Name]],4,0) -> Road Maintenance | G7: 450000 | H7: 250000 | I7: =G7-H7 -> 200000 | J7: 46231 | K7: Partially Received

Sheet Expense Tracker
A1: EXPENSE TRACKER
A2: Expense ID | B2: Date | C2: Company ID | D2: Tender ID | E2: Company Name | F2: Tender Name | G2: Expense Category | H2: Description | I2: Amount (₹) | J2: Bill / Voucher No
A3: E001 | B3: 46174 | C3: C001 | D3: T001 | E3: {=_xlfn.XLOOKUP(C3,'Tender Master Data'!$B$3:$B$7,'Tender Master Data'!$C$3:$C$7)} -> Micky Services Pvt Ltd | F3: {=_xlfn.XLOOKUP(D3,'Tender Master Data'!$A$3:$A$7,'Tender Master Data'!$D$3:$D$7)} -> Hospital Housekeeping | G3: Salary | H3: Staff salary - June | I3: 45000 | J3: INV-101
A4: E002 | B4: 46175 | C4: C001 | D4: T001 | E4: {=_xlfn.XLOOKUP(C4,'Tender Master Data'!$B$3:$B$7,'Tender Master Data'!$C$3:$C$7)} -> Micky Services Pvt Ltd | F4: {=_xlfn.XLOOKUP(D4,'Tender Master Data'!$A$3:$A$7,'Tender Master Data'!$D$3:$D$7)} -> Hospital Housekeeping | G4: Travel | H4: Local travel | I4: 5000 | J4: INV-102
A5: E003 | B5: 46176 | C5: C001 | D5: T002 | E5: {=_xlfn.XLOOKUP(C5,'Tender Master Data'!$B$3:$B$7,'Tender Master Data'!$C$3:$C$7)} -> Micky Services Pvt Ltd | F5: {=_xlfn.XLOOKUP(D5,'Tender Master Data'!$A$3:$A$7,'Tender Master Data'!$D$3:$D$7)} -> Office Manpower | G5: Food | H5: Staff meal | I5: 2500 | J5: INV-103
A6: E004 | B6: 46177 | C6: C002 | D6: T003 | E6: {=_xlfn.XLOOKUP(C6,'Tender Master Data'!$B$3:$B$7,'Tender Master Data'!$C$3:$C$7)} -> ABC Facility Solutions | F6: {=_xlfn.XLOOKUP(D6,'Tender Master Data'!$A$3:$A$7,'Tender Master Data'!$D$3:$D$7)} -> Campus Security | G6: Equipment | H6: Safety equipment | I6: 18000 | J6: INV-104
A7: E005 | B7: 46179 | C7: C002 | D7: T004 | E7: {=_xlfn.XLOOKUP(C7,'Tender Master Data'!$B$3:$B$7,'Tender Master Data'!$C$3:$C$7)} -> ABC Facility Solutions | F7: {=_xlfn.XLOOKUP(D7,'Tender Master Data'!$A$3:$A$7,'Tender Master Data'!$D$3:$D$7)} -> Office Cleaning | G7: Travel | H7: Site visit | I7: 3200 | J7: INV-105
A8: E006 | B8: 46205 | C8: C003 | D8: T005 | E8: {=_xlfn.XLOOKUP(C8,'Tender Master Data'!$B$3:$B$7,'Tender Master Data'!$C$3:$C$7)} -> XYZ Infra Services | F8: {=_xlfn.XLOOKUP(D8,'Tender Master Data'!$A$3:$A$7,'Tender Master Data'!$D$3:$D$7)} -> Road Maintenance | G8: Material | H8: Repair material | I8: 27500 | J8: INV-106
A9: E007 | B9: 46208 | C9: C001 | D9: T001 | E9: {=_xlfn.XLOOKUP(C9,'Tender Master Data'!$B$3:$B$7,'Tender Master Data'!$C$3:$C$7)} -> Micky Services Pvt Ltd | F9: {=_xlfn.XLOOKUP(D9,'Tender Master Data'!$A$3:$A$7,'Tender Master Data'!$D$3:$D$7)} -> Hospital Housekeeping | G9: Other | H9: Printing and stationery | I9: 1800 | J9: INV-107
A10: E008 | B10: 46211 | C10: C002 | D10: T003 | E10: {=_xlfn.XLOOKUP(C10,'Tender Master Data'!$B$3:$B$7,'Tender Master Data'!$C$3:$C$7)} -> ABC Facility Solutions | F10: {=_xlfn.XLOOKUP(D10,'Tender Master Data'!$A$3:$A$7,'Tender Master Data'!$D$3:$D$7)} -> Campus Security | G10: Food | H10: Staff meal | I10: 2200 | J10: INV-108

Sheet Supervisor Tracker
A1: SUPERVISOR TRACKER
A2: Entry ID | B2: Date | C2: Company ID | D2: Tender ID | E2: Company Name | F2: Tender Name | G2: Supervisor | H2: Amount Given (₹) | I2: Expense Used (₹) | J2: Amount Returned (₹) | K2: Balance With Supervisor (₹)
A3: SUP001 | B3: 46174 | C3: C001 | D3: T001 | E3: =VLOOKUP(C3,SalaryTracker[[#ALL],[Company ID]:[Company Name]],3,0) -> Micky Services Pvt Ltd | F3: =vlookup(D3,SalaryTracker[[#ALL],[Tender ID]:[Tender Name]],3,0) -> Hospital Housekeeping | G3: Shivam | H3: 50000 | I3: 30000 | J3: 10000 | K3: =H3-I3-J3 -> 10000
A4: SUP002 | B4: 46178 | C4: C002 | D4: T003 | E4: =VLOOKUP(C4,SalaryTracker[[#ALL],[Company ID]:[Company Name]],3,0) -> ABC Facility Solutions | F4: =vlookup(D4,SalaryTracker[[#ALL],[Tender ID]:[Tender Name]],3,0) -> Campus Security | G4: Rohit | H4: 40000 | I4: 22000 | J4: 8000 | K4: =H4-I4-J4 -> 10000
A5: SUP003 | B5: 46204 | C5: C003 | D5: T005 | E5: =VLOOKUP(C5,SalaryTracker[[#ALL],[Company ID]:[Company Name]],3,0) -> XYZ Infra Services | F5: =vlookup(D5,SalaryTracker[[#ALL],[Tender ID]:[Tender Name]],3,0) -> Road Maintenance | G5: Aman | H5: 35000 | I5: 20000 | J5: 5000 | K5: =H5-I5-J5 -> 10000

Sheet Salary Tracker
A1: SALARY TRACKER
A2: Salary ID | B2: Payment Date | C2: Company ID | D2: Tender ID | E2: Company Name | F2: Tender Name | G2: Employee Name | H2: Salary Payable (₹) | I2: Paid (₹) | J2: Pending (₹) | K2: Salary Month
A3: S001 | B3: 46174 | C3: C001 | D3: T001 | E3: {=_xlfn.XLOOKUP(C3,'Expense Tracker'!$C$3:$C$10,'Expense Tracker'!$E$3:$E$10)} -> Micky Services Pvt Ltd | F3: {=_xlfn.xlookup(D3,'Expense Tracker'!$D$3:$D$10,'Expense Tracker'!$F$3:$F$10)} -> Hospital Housekeeping | G3: Rahul | H3: 25000 | I3: 25000 | J3: =H3-I3 -> 0 | K3: June 2026
A4: S002 | B4: 46174 | C4: C001 | D4: T001 | E4: {=_xlfn.XLOOKUP(C4,'Expense Tracker'!$C$3:$C$10,'Expense Tracker'!$E$3:$E$10)} -> Micky Services Pvt Ltd | F4: {=_xlfn.xlookup(D4,'Expense Tracker'!$D$3:$D$10,'Expense Tracker'!$F$3:$F$10)} -> Hospital Housekeeping | G4: Amit | H4: 20000 | I4: 15000 | J4: =H4-I4 -> 5000 | K4: June 2026
A5: S003 | B5: 46174 | C5: C001 | D5: T002 | E5: {=_xlfn.XLOOKUP(C5,'Expense Tracker'!$C$3:$C$10,'Expense Tracker'!$E$3:$E$10)} -> Micky Services Pvt Ltd | F5: {=_xlfn.xlookup(D5,'Expense Tracker'!$D$3:$D$10,'Expense Tracker'!$F$3:$F$10)} -> Office Manpower | G5: Neha | H5: 22000 | I5: 22000 | J5: =H5-I5 -> 0 | K5: June 2026
A6: S004 | B6: 46174 | C6: C002 | D6: T003 | E6: {=_xlfn.XLOOKUP(C6,'Expense Tracker'!$C$3:$C$10,'Expense Tracker'!$E$3:$E$10)} -> ABC Facility Solutions | F6: {=_xlfn.xlookup(D6,'Expense Tracker'!$D$3:$D$10,'Expense Tracker'!$F$3:$F$10)} -> Campus Security | G6: Priya | H6: 24000 | I6: 24000 | J6: =H6-I6 -> 0 | K6: June 2026
A7: S005 | B7: 46204 | C7: C003 | D7: T005 | E7: {=_xlfn.XLOOKUP(C7,'Expense Tracker'!$C$3:$C$10,'Expense Tracker'!$E$3:$E$10)} -> XYZ Infra Services | F7: {=_xlfn.xlookup(D7,'Expense Tracker'!$D$3:$D$10,'Expense Tracker'!$F$3:$F$10)} -> Road Maintenance | G7: Rishabh | H7: 26000 | I7: 20000 | J7: =H7-I7 -> 6000 | K7: July 2026

Sheet FDR-BG Tracker
A1: FDR / BG TRACKER
A2: Reference ID | B2: Company ID | C2: Tender ID | D2: Company Name | E2: Tender Name | F2: Type | G2: Amount (₹) | H2: Bank | I2: Issue Date | J2: Expiry Date | K2: Status
A3: FDR001 | B3: C001 | C3: T001 | D3: =VLOOKUP(B3,SupervisorTracker[[#ALL],[Company ID]:[Company Name]],3,0) -> Micky Services Pvt Ltd | E3: =vlookup(C3,SupervisorTracker[[#ALL],[Tender ID]:[Tender Name]],3,0) -> Hospital Housekeeping | F3: FDR | G3: 200000 | H3: SBI | I3: 46113 | J3: 46477 | K3: Active
A4: FDR002 | B4: C002 | C4: T003 | D4: =VLOOKUP(B4,SupervisorTracker[[#ALL],[Company ID]:[Company Name]],3,0) -> ABC Facility Solutions | E4: =vlookup(C4,SupervisorTracker[[#ALL],[Tender ID]:[Tender Name]],3,0) -> Campus Security | F4: BG | G4: 150000 | H4: HDFC | I4: 46174 | J4: 46538 | K4: Active
A5: FDR003 | B5: C003 | C5: T005 | D5: =VLOOKUP(B5,SupervisorTracker[[#ALL],[Company ID]:[Company Name]],3,0) -> XYZ Infra Services | E5: =vlookup(C5,SupervisorTracker[[#ALL],[Tender ID]:[Tender Name]],3,0) -> Road Maintenance | F5: FDR | G5: 100000 | H5: ICICI | I5: 46127 | J5: 46491 | K5: Active

Sheet Bank Transactions
A1: BANK TRANSACTIONS
A2: Transaction ID | B2: Date | C2: Company ID | D2: Tender ID | E2: Company Name | F2: Tender Name | G2: Transaction Type | H2: Amount (₹) | I2: Description
A3: B001 | B3: 46174 | C3: C001 | D3: T001 | E3: {=iferror(VLOOKUP(C3:C998,FDRBGTracker[[#ALL],[Company ID]:[Company Name]],3,0),"")} -> Micky Services Pvt Ltd | F3: {=iferror(VLOOKUP(D3:D998,FDRBGTracker[[#ALL],[Tender ID]:[Tender Name]],3,0),"")} -> Hospital Housekeeping | G3: Opening Balance | H3: 250000 | I3: Opening balance for sample
A4: B002 | B4: 46178 | C4: C001 | D4: T001 | E4: Micky Services Pvt Ltd | F4: Hospital Housekeeping | G4: Credit | H4: 300000 | I4: RA001 payment received
A5: B003 | B5: 46179 | C5: C001 | D5: T001 | E5: Micky Services Pvt Ltd | F5: Hospital Housekeeping | G5: Debit | H5: 50000 | I5: Salary and site expenses
A6: B004 | B6: 46188 | C6: C002 | D6: T003 | E6: ABC Facility Solutions | F6: Campus Security | G6: Credit | H6: 200000 | I6: RA003 part payment
A7: B005 | B7: 46189 | C7: C002 | D7: T003 | E7: ABC Facility Solutions | F7: Campus Security | G7: Debit | H7: 25000 | I7: Site expenses
A8: B006 | B8: 46204 | C8: C003 | D8: T005 | E8: XYZ Infra Services | F8: Road Maintenance | G8: Opening Balance | H8: 150000 | I8: Opening balance for sample
A9: B007 | B9: 46215 | C9: C003 | D9: T005 | E9: XYZ Infra Services | F9: Road Maintenance | G9: Credit | H9: 250000 | I9: RA005 part payment
A10: B008 | B10: 46216 | C10: C003 | D10: T005 | E10: XYZ Infra Services | F10: Road Maintenance | G10: Debit | H10: 40000 | I10: Material and labour
